<?xml version="1.0" encoding="utf-8"?>
<odoo>
    <data noupdate="0">
<!-- Record Email Template -->
<!-- Record SMS Template -->
<!-- Record Mobile Template -->
<!-- Record Notifications -->
        <record model="ir.sequence" id="seq_smartbiz_stock_transfer_request_tr">
            <field name="name">Transfer Request</field>
            <field name="code">smartbiz_stock.transfer_request</field>
            <field name="prefix">TR</field>
            <field name="padding">5</field>
            <field name="company_id" eval = "False" />
        </record>

<!-- Auto Schedule -->

    </data>
</odoo>
